{
  "id": "329d99be000b",
  "name": "Custom Fantasy",
  "description": "A magical fantasy style",
  "base_prompt": "",
  "negative_prompt": "",
  "style_type": "disney_3d",
  "seed": -1,
  "cfg_scale": 7.5,
  "steps": 30,
  "sampler": "dpmpp_2m",
  "ip_adapter_ref": null,
  "ip_adapter_scale": 0.8,
  "lora_weights": null,
  "lora_scale": 1.0,
  "lighting_type": "dramatic",
  "color_palette": "pastel",
  "rendering_type": "cel_shaded",
  "extra_params": {},
  "is_default": false,
  "created_at": "2026-04-05T16:23:38.075664",
  "updated_at": "2026-04-05T16:23:38.205405",
  "tags": [
    "fantasy",
    "magical"
  ],
  "metadata": {},
  "usage_count": 1,
  "last_used_at": "2026-04-05T16:23:38.205405"
}